{
  "FlightStatusResource": {
    "Flights": {
      "Flight": [
        {
          "Departure": {
            "AirportCode": "LHR",
            "ScheduledTimeLocal": {
              "DateTime": "2026-03-12T14:35"
            },
            "ScheduledTimeUTC": {
              "DateTime": "2026-03-12T14:35Z"
            },
            "TimeStatus": {
              "Code": "OT",
              "Definition": "Flight On Time"
            },
            "Terminal": {
              "Name": "2"
            }
          },
          "Arrival": {
            "AirportCode": "STR",
            "ScheduledTimeLocal": {
              "DateTime": "2026-03-12T17:15"
            },
            "ScheduledTimeUTC": {
              "DateTime": "2026-03-12T16:15Z"
            },
            "TimeStatus": {
              "Code": "OT",
              "Definition": "Flight On Time"
            },
            "Terminal": {
              "Name": "3"
            }
          },
          "MarketingCarrier": {
            "AirlineID": "EW",
            "FlightNumber": "2463"
          },
          "OperatingCarrier": {
            "AirlineID": "EW",
            "FlightNumber": "2463"
          },
          "Equipment": {
            "AircraftCode": "31D",
            "AircraftRegistration": "DABGJ"
          },
          "FlightStatus": {
            "Code": "NA",
            "Definition": "No status"
          },
          "ServiceType": "Passenger"
        },
        {
          "Departure": {
            "AirportCode": "LHR",
            "ScheduledTimeLocal": {
              "DateTime": "2026-03-12T18:35"
            },
            "ScheduledTimeUTC": {
              "DateTime": "2026-03-12T18:35Z"
            },
            "TimeStatus": {
              "Code": "OT",
              "Definition": "Flight On Time"
            },
            "Terminal": {
              "Name": "2"
            }
          },
          "Arrival": {
            "AirportCode": "STR",
            "ScheduledTimeLocal": {
              "DateTime": "2026-03-12T21:15"
            },
            "ScheduledTimeUTC": {
              "DateTime": "2026-03-12T20:15Z"
            },
            "TimeStatus": {
              "Code": "OT",
              "Definition": "Flight On Time"
            },
            "Terminal": {
              "Name": "3"
            }
          },
          "MarketingCarrier": {
            "AirlineID": "EW",
            "FlightNumber": "2465"
          },
          "OperatingCarrier": {
            "AirlineID": "EW",
            "FlightNumber": "2465"
          },
          "Equipment": {
            "AircraftCode": "31D",
            "AircraftRegistration": "DAGWP"
          },
          "FlightStatus": {
            "Code": "NA",
            "Definition": "No status"
          },
          "ServiceType": "Passenger"
        }
      ]
    },
    "Meta": {
      "@Version": "1.0.0",
      "Link": [
        {
          "@Href": "https://api.lufthansa.com/v1/operations/flightstatus/route/LHR/STR/2026-03-12",
          "@Rel": "self"
        },
        {
          "@Href": "https://api.lufthansa.com/v1/mds-references/airports/{airportCode}",
          "@Rel": "related"
        }
      ],
      "TotalCount": 2
    }
  }
}